{
  "_data": {
    "title": "Ms.",
    "otherTitle": null,
    "firstName": "Susan",
    "middleName": "Carrington",
    "lastName": "Carrington",
    "dateOfBirth": "1995-06-29T07:05:25.166Z",
    "landline": null,
    "fax": null,
    "mobile": "2916503771",
    "email": "Karl_Emard-Boyer5@hotmail.com",
    "doNotContact": false,
    "emailValidated": false,
    "address": {
      "pafOrganisationName": null,
      "flatName": null,
      "buildingNumberRange": null,
      "buildingName": "26",
      "street": "Kirlin Mews",
      "city": "Nether Lakin",
      "county": "Lothian",
      "postalCode": "OQ03 4NB",
      "country": "United Kingdom",
      "uprn": null,
      "dependentLocality": null,
      "doubleDependentLocality": null,
      "addressTypeId": null
    },
    "locked": false,
    "id": 5692562,
    "confirmed": null,
    "customerReferenceNumber": "1420664271",
    "personalIdentifiers": null,
    "deactivated": false
  }
}