{
  "notifications": [
    {
      "id": 2027877,
      "personId": 5263421,
      "organisationId": "5565448",
      "messageId": 7668364,
      "readAt": 27000,
      "archivedAt": null,
      "archive": null,
      "createdAt": 9977452223322,
      "title": "Permission changed for Nicholas SANGSTER",
      "body": "<p>Your permission for Nicholas SANGSTER was changed on Tue Jun 07 2022</p>",
      "category": "OrganisationLevel",
      "bespokeNotificationId": null
    },
    {
      "id": 7400514,
      "personId": 5263421,
      "organisationId": "5565448",
      "messageId": 2043839,
      "readAt": null,
      "archivedAt": null,
      "archive": null,
      "createdAt": 2984852488101,
      "title": "Permission changed for Nicholas SANGSTER",
      "body": "<p>Your permission for Nicholas SANGSTER was changed on Wed Jun 07 2023</p>",
      "category": "OrganisationLevel",
      "bespokeNotificationId": null
    },
    {
      "id": 7706658,
      "personId": 5263421,
      "organisationId": "5565448",
      "messageId": 1124864,
      "readAt": 13000,
      "archivedAt": null,
      "archive": null,
      "createdAt": 7101527484671,
      "title": "Permission changed for Nicholas SANGSTER",
      "body": "<p>Your permission for Nicholas SANGSTER was changed on Sun Jun 18 2023</p>",
      "category": "OrganisationLevel",
      "bespokeNotificationId": null
    },
    {
      "id": 8414560,
      "personId": 5263421,
      "organisationId": "5565448",
      "messageId": 5196177,
      "readAt": null,
      "archivedAt": null,
      "archive": null,
      "createdAt": 969275214547,
      "title": "Permission changed for Nicholas SANGSTER",
      "body": "<p>Your permission for Nicholas SANGSTER was changed on Mon Apr 15 2024</p>",
      "category": "OrganisationLevel",
      "bespokeNotificationId": null
    },
    {
      "id": 7252310,
      "personId": 5263421,
      "organisationId": "5565448",
      "messageId": 7154931,
      "readAt": null,
      "archivedAt": null,
      "archive": null,
      "createdAt": 2193484887021,
      "title": "Permission changed for Nicholas SANGSTER",
      "body": "<p>Your permission for Nicholas SANGSTER was changed on Tue Aug 08 2023</p>",
      "category": "OrganisationLevel",
      "bespokeNotificationId": null
    },
    {
      "id": 7047537,
      "personId": 5263421,
      "organisationId": "5565448",
      "messageId": 9325712,
      "readAt": null,
      "archivedAt": null,
      "archive": null,
      "createdAt": 2482651190316,
      "title": "Permission changed for Nicholas SANGSTER",
      "body": "<p>Your permission for Nicholas SANGSTER was changed on Thu Jul 28 2022</p>",
      "category": "OrganisationLevel",
      "bespokeNotificationId": null
    },
    {
      "id": 14661,
      "personId": 5263421,
      "organisationId": "5565448",
      "messageId": 1649395,
      "readAt": 9000,
      "archivedAt": null,
      "archive": null,
      "createdAt": 1959913864101,
      "title": "Permission changed for Nicholas SANGSTER",
      "body": "<p>Your permission for Nicholas SANGSTER was changed on Tue Jan 31 2023</p>",
      "category": "OrganisationLevel",
      "bespokeNotificationId": null
    }
  ],
  "resultCount": 7,
  "readCount": 3,
  "unreadCount": 4
}