{
  "notifications": [
    {
      "id": 4686592,
      "personId": 5776865,
      "organisationId": "5625145",
      "messageId": 2706508,
      "readAt": null,
      "archivedAt": null,
      "archive": null,
      "createdAt": 1664187860985,
      "title": "Permission changed for Charlotte Jacques",
      "body": "<p>Your permission for Charlotte Jacques was changed on Thu Apr 27 2023</p>",
      "category": "OrganisationLevel",
      "bespokeNotificationId": null
    },
    {
      "id": 9352609,
      "personId": 5776865,
      "organisationId": "5625145",
      "messageId": 8412248,
      "readAt": 3000,
      "archivedAt": null,
      "archive": null,
      "createdAt": 6413716129603,
      "title": "Permission changed for Charlotte Jacques",
      "body": "<p>Your permission for Charlotte Jacques was changed on Thu Mar 14 2024</p>",
      "category": "OrganisationLevel",
      "bespokeNotificationId": null
    },
    {
      "id": 160302,
      "personId": 5776865,
      "organisationId": "5625145",
      "messageId": 6356475,
      "readAt": null,
      "archivedAt": null,
      "archive": null,
      "createdAt": 7142073116902,
      "title": "Permission changed for Charlotte Jacques",
      "body": "<p>Your permission for Charlotte Jacques was changed on Mon Dec 05 2022</p>",
      "category": "OrganisationLevel",
      "bespokeNotificationId": null
    },
    {
      "id": 3924893,
      "personId": 5776865,
      "organisationId": "5625145",
      "messageId": 484976,
      "readAt": null,
      "archivedAt": null,
      "archive": null,
      "createdAt": 685534764906,
      "title": "Permission changed for Charlotte Jacques",
      "body": "<p>Your permission for Charlotte Jacques was changed on Thu May 16 2024</p>",
      "category": "OrganisationLevel",
      "bespokeNotificationId": null
    },
    {
      "id": 5869165,
      "personId": 5776865,
      "organisationId": "5625145",
      "messageId": 2149035,
      "readAt": 2000,
      "archivedAt": null,
      "archive": null,
      "createdAt": 3790934342023,
      "title": "Permission changed for Charlotte Jacques",
      "body": "<p>Your permission for Charlotte Jacques was changed on Wed Feb 08 2023</p>",
      "category": "OrganisationLevel",
      "bespokeNotificationId": null
    },
    {
      "id": 7070067,
      "personId": 5776865,
      "organisationId": "5625145",
      "messageId": 2284650,
      "readAt": null,
      "archivedAt": null,
      "archive": null,
      "createdAt": 2374960653685,
      "title": "Permission changed for Charlotte Jacques",
      "body": "<p>Your permission for Charlotte Jacques was changed on Wed Sep 28 2022</p>",
      "category": "OrganisationLevel",
      "bespokeNotificationId": null
    },
    {
      "id": 1574184,
      "personId": 5776865,
      "organisationId": "5625145",
      "messageId": 6046743,
      "readAt": 24000,
      "archivedAt": null,
      "archive": null,
      "createdAt": 5111099376015,
      "title": "Permission changed for Charlotte Jacques",
      "body": "<p>Your permission for Charlotte Jacques was changed on Sun Nov 26 2023</p>",
      "category": "OrganisationLevel",
      "bespokeNotificationId": null
    },
    {
      "id": 3694132,
      "personId": 5776865,
      "organisationId": "5625145",
      "messageId": 1518028,
      "readAt": null,
      "archivedAt": null,
      "archive": null,
      "createdAt": 7026585831781,
      "title": "Permission changed for Charlotte Jacques",
      "body": "<p>Your permission for Charlotte Jacques was changed on Thu Oct 05 2023</p>",
      "category": "OrganisationLevel",
      "bespokeNotificationId": null
    },
    {
      "id": 9473846,
      "personId": 5776865,
      "organisationId": "5625145",
      "messageId": 2211123,
      "readAt": null,
      "archivedAt": null,
      "archive": null,
      "createdAt": 5119922688300,
      "title": "Permission changed for Charlotte Jacques",
      "body": "<p>Your permission for Charlotte Jacques was changed on Sun Aug 13 2023</p>",
      "category": "OrganisationLevel",
      "bespokeNotificationId": null
    },
    {
      "id": 9575375,
      "personId": 5776865,
      "organisationId": "5625145",
      "messageId": 8741659,
      "readAt": null,
      "archivedAt": null,
      "archive": null,
      "createdAt": 1706360638779,
      "title": "Permission changed for Charlotte Jacques",
      "body": "<p>Your permission for Charlotte Jacques was changed on Sun Jun 09 2024</p>",
      "category": "OrganisationLevel",
      "bespokeNotificationId": null
    }
  ],
  "resultCount": 10,
  "readCount": 3,
  "unreadCount": 7
}