{
  "notifications": [
    {
      "id": 7370068,
      "personId": 5331098,
      "organisationId": "5565448",
      "messageId": 9601971,
      "readAt": null,
      "archivedAt": null,
      "archive": null,
      "createdAt": 3200947615636,
      "title": "Permission changed for Marcus Twigden",
      "body": "<p>Your permission for Marcus Twigden was changed on Sun Nov 19 2023</p>",
      "category": "OrganisationLevel",
      "bespokeNotificationId": null
    },
    {
      "id": 9575912,
      "personId": 5331098,
      "organisationId": "5565448",
      "messageId": 8875574,
      "readAt": null,
      "archivedAt": null,
      "archive": null,
      "createdAt": 8175871897573,
      "title": "Permission changed for Marcus Twigden",
      "body": "<p>Your permission for Marcus Twigden was changed on Sun Mar 05 2023</p>",
      "category": "OrganisationLevel",
      "bespokeNotificationId": null
    },
    {
      "id": 6938186,
      "personId": 5331098,
      "organisationId": "5565448",
      "messageId": 353420,
      "readAt": null,
      "archivedAt": null,
      "archive": null,
      "createdAt": 1906376607631,
      "title": "Permission changed for Marcus Twigden",
      "body": "<p>Your permission for Marcus Twigden was changed on Thu Jun 15 2023</p>",
      "category": "OrganisationLevel",
      "bespokeNotificationId": null
    },
    {
      "id": 4662170,
      "personId": 5331098,
      "organisationId": "5565448",
      "messageId": 4034876,
      "readAt": 19000,
      "archivedAt": null,
      "archive": null,
      "createdAt": 8506497176372,
      "title": "Permission changed for Marcus Twigden",
      "body": "<p>Your permission for Marcus Twigden was changed on Sun Jul 24 2022</p>",
      "category": "OrganisationLevel",
      "bespokeNotificationId": null
    },
    {
      "id": 1438015,
      "personId": 5331098,
      "organisationId": "5565448",
      "messageId": 5951918,
      "readAt": 12000,
      "archivedAt": null,
      "archive": null,
      "createdAt": 9902843328319,
      "title": "Permission changed for Marcus Twigden",
      "body": "<p>Your permission for Marcus Twigden was changed on Sun Feb 19 2023</p>",
      "category": "OrganisationLevel",
      "bespokeNotificationId": null
    },
    {
      "id": 8486906,
      "personId": 5331098,
      "organisationId": "5565448",
      "messageId": 9880034,
      "readAt": null,
      "archivedAt": null,
      "archive": null,
      "createdAt": 2138566115110,
      "title": "Permission changed for Marcus Twigden",
      "body": "<p>Your permission for Marcus Twigden was changed on Wed Apr 19 2023</p>",
      "category": "OrganisationLevel",
      "bespokeNotificationId": null
    },
    {
      "id": 7755292,
      "personId": 5331098,
      "organisationId": "5565448",
      "messageId": 7304621,
      "readAt": 15000,
      "archivedAt": null,
      "archive": null,
      "createdAt": 9515487155313,
      "title": "Permission changed for Marcus Twigden",
      "body": "<p>Your permission for Marcus Twigden was changed on Sat May 20 2023</p>",
      "category": "OrganisationLevel",
      "bespokeNotificationId": null
    },
    {
      "id": 7468229,
      "personId": 5331098,
      "organisationId": "5565448",
      "messageId": 2614487,
      "readAt": null,
      "archivedAt": null,
      "archive": null,
      "createdAt": 2330087985821,
      "title": "Permission changed for Marcus Twigden",
      "body": "<p>Your permission for Marcus Twigden was changed on Wed Jul 26 2023</p>",
      "category": "OrganisationLevel",
      "bespokeNotificationId": null
    },
    {
      "id": 9359672,
      "personId": 5331098,
      "organisationId": "5565448",
      "messageId": 2301237,
      "readAt": null,
      "archivedAt": null,
      "archive": null,
      "createdAt": 2106144858101,
      "title": "Permission changed for Marcus Twigden",
      "body": "<p>Your permission for Marcus Twigden was changed on Thu Oct 06 2022</p>",
      "category": "OrganisationLevel",
      "bespokeNotificationId": null
    }
  ],
  "resultCount": 9,
  "readCount": 3,
  "unreadCount": 6
}